django_pypal
