Metadata-Version: 1.0
Name: django-pypal
Version: 0.1.0
Summary: Django app for PyPal
Home-page: https://github.com/jarcoal/django-pypal
Author: Jared Morse
Author-email: jarcoal@gmail.com
License: BSD
Keywords: django,pypal,paypal
Platform: UNKNOWN
Classifier: Programming Language :: Python
Classifier: Topic :: Software Development :: Libraries :: Python Modules
Classifier: Framework :: Django
Classifier: Environment :: Web Environment
